{"Toy": ["icon/Toy/water-gun.png", "icon/Toy/toys.png", "icon/Toy/toy-train.png", "icon/Toy/construction.png", "icon/Toy/rocking-horse.png"], "Shopping": ["icon/Shopping/shirt.png", "icon/Shopping/Shopping.png", "icon/Shopping/wardrobe.png", "icon/Shopping/dress.png"], "Entertainment": ["icon/Entertainment/popcorn.png", "icon/Entertainment/Gaming.png", "icon/Entertainment/Party.png", "icon/Entertainment/casino_chips.png"], "Food": ["icon/Food/cake.png", "icon/Food/fast_food.png", "icon/Food/hamburger.png", "icon/Food/pizza.png", "icon/Food/french_fries.png", "icon/Food/healthy_eating.png", "icon/Food/diet.png"], "Bill": ["icon/Bill/Gas_Bill.png", "icon/Bill/Wifi_Bill.png", "icon/Bill/payment.png", "icon/Bill/receipt.png", "icon/Bill/Water_Bill.png", "icon/Bill/Electricity_Bill.png", "icon/Bill/telephone.png", "icon/Bill/bill.png"], "Heath": ["icon/Heath/Heath.png", "icon/Heath/Beauty.png"], "Other": ["icon/Other/others.png", "icon/Other/Sport.png", "icon/Other/tax.png", "icon/Other/insurance.png", "icon/Other/electronic.png", "icon/Other/Pet.png", "icon/Other/baby.png", "icon/Other/furniture.png"], "Transportation": ["icon/Transportation/airplane.png", "icon/Transportation/car.png", "icon/Transportation/bus.png", "icon/Transportation/tram.png"], "Education": ["icon/Education/book.png", "icon/Education/school.png"], "Drink": ["icon/Drink/Whine.png", "icon/Drink/coffee_cup.png", "icon/Drink/beer.png", "icon/Drink/latte.png", "icon/Drink/bubble_tea.png"]}